odoo8_addon_web_menu_autohide-8.0.1.0.0-py2.7-nspkg.pth
odoo_addons/web_menu_autohide/__openerp__.py
odoo_addons/web_menu_autohide/__init__.py
odoo_addons/web_menu_autohide/README.rst
odoo_addons/web_menu_autohide/views/templates.xml
odoo_addons/web_menu_autohide/data/ir_config_parameter.xml
odoo_addons/web_menu_autohide/static/description/icon.png
odoo_addons/web_menu_autohide/static/src/js/web_menu_autohide.js
odoo8_addon_web_menu_autohide-8.0.1.0.0.dist-info/top_level.txt
odoo8_addon_web_menu_autohide-8.0.1.0.0.dist-info/WHEEL
odoo8_addon_web_menu_autohide-8.0.1.0.0.dist-info/RECORD
odoo8_addon_web_menu_autohide-8.0.1.0.0.dist-info/metadata.json
odoo8_addon_web_menu_autohide-8.0.1.0.0.dist-info/DESCRIPTION.rst
odoo8_addon_web_menu_autohide-8.0.1.0.0.dist-info/METADATA
odoo8_addon_web_menu_autohide-8.0.1.0.0.dist-info/namespace_packages.txt
